odoo9_addon_l10n_ch_import_winbiz-9.0.1.0.1-py2.7-nspkg.pth
odoo_addons/l10n_ch_import_winbiz/__openerp__.py
odoo_addons/l10n_ch_import_winbiz/__init__.py
odoo_addons/l10n_ch_import_winbiz/README.rst
odoo_addons/l10n_ch_import_winbiz/security/security.xml
odoo_addons/l10n_ch_import_winbiz/models/account_journal.py
odoo_addons/l10n_ch_import_winbiz/models/__init__.py
odoo_addons/l10n_ch_import_winbiz/i18n/zh_CN.po
odoo_addons/l10n_ch_import_winbiz/i18n/nb_NO.po
odoo_addons/l10n_ch_import_winbiz/i18n/pt.po
odoo_addons/l10n_ch_import_winbiz/i18n/it.po
odoo_addons/l10n_ch_import_winbiz/i18n/es.po
odoo_addons/l10n_ch_import_winbiz/i18n/tr.po
odoo_addons/l10n_ch_import_winbiz/i18n/hr.po
odoo_addons/l10n_ch_import_winbiz/i18n/bg.po
odoo_addons/l10n_ch_import_winbiz/i18n/gl.po
odoo_addons/l10n_ch_import_winbiz/i18n/ca.po
odoo_addons/l10n_ch_import_winbiz/i18n/sl.po
odoo_addons/l10n_ch_import_winbiz/i18n/es_ES.po
odoo_addons/l10n_ch_import_winbiz/i18n/pt_PT.po
odoo_addons/l10n_ch_import_winbiz/i18n/nl.po
odoo_addons/l10n_ch_import_winbiz/i18n/l10n_ch_import_winbiz.pot
odoo_addons/l10n_ch_import_winbiz/i18n/am.po
odoo_addons/l10n_ch_import_winbiz/i18n/de.po
odoo_addons/l10n_ch_import_winbiz/i18n/fr.po
odoo_addons/l10n_ch_import_winbiz/i18n/pt_BR.po
odoo_addons/l10n_ch_import_winbiz/i18n/el_GR.po
odoo_addons/l10n_ch_import_winbiz/i18n/fi.po
odoo_addons/l10n_ch_import_winbiz/i18n/hr_HR.po
odoo_addons/l10n_ch_import_winbiz/wizard/l10n_ch_import_winbiz_view.xml
odoo_addons/l10n_ch_import_winbiz/wizard/l10n_ch_import_winbiz.py
odoo_addons/l10n_ch_import_winbiz/wizard/__init__.py
odoo_addons/l10n_ch_import_winbiz/views/menu.xml
odoo_addons/l10n_ch_import_winbiz/views/account_journal_view.xml
odoo_addons/l10n_ch_import_winbiz/utils/__init__.py
odoo_addons/l10n_ch_import_winbiz/utils/importers.py
odoo_addons/l10n_ch_import_winbiz/tests/golden-output.txt
odoo_addons/l10n_ch_import_winbiz/tests/test_import.py
odoo9_addon_l10n_ch_import_winbiz-9.0.1.0.1.dist-info/top_level.txt
odoo9_addon_l10n_ch_import_winbiz-9.0.1.0.1.dist-info/WHEEL
odoo9_addon_l10n_ch_import_winbiz-9.0.1.0.1.dist-info/RECORD
odoo9_addon_l10n_ch_import_winbiz-9.0.1.0.1.dist-info/metadata.json
odoo9_addon_l10n_ch_import_winbiz-9.0.1.0.1.dist-info/DESCRIPTION.rst
odoo9_addon_l10n_ch_import_winbiz-9.0.1.0.1.dist-info/METADATA
odoo9_addon_l10n_ch_import_winbiz-9.0.1.0.1.dist-info/namespace_packages.txt
