Metadata-Version: 2.0
Name: odoo9-addon-l10n-ch-import-winbiz
Version: 9.0.1.0.1
Summary: Accounting Import WinBIZ
Home-page: https://opennet.ch
Author: Open Net Sàrl, Camptocamp, Odoo Community Association (OCA)
Author-email: support@odoo-community.org
License: AGPL-3
Platform: UNKNOWN
Requires-Dist: odoo (<9.1a,>=9.0a)
Requires-Dist: xlrd
Classifier: Programming Language :: Python :: 2.7
Classifier: Framework :: Odoo
Classifier: License :: OSI Approved :: GNU Affero General Public License v3
